{
    "shoplifting": {
        "sallys_sweet_shop": [
            {
                "title": "One camera",
                "disabled": false,
                "CHANGE?": "No!!",
                "this_run_time": "03:28:18",
                "run_type": "wait for it...",
                "old_run": "00:45:44",
                "min_cycle": "timedelta(hours=3)",
                "max_cycle": "timedelta(hours=10)",
                "status": "In sallys_sweet_shop the One camera is active, can be disable off any minute, max in 6h 31m."
            }
        ],
        "Bits_n_bobs": [
            {
                "title": "Two cameras",
                "disabled": false,
                "CHANGE?": "No!!",
                "this_run_time": "09:42:44",
                "run_type": "wait for it...",
                "old_run": "00:16:15",
                "min_cycle": "timedelta(hours=4, minutes=30)",
                "max_cycle": "timedelta(hours=14)",
                "status": "In Bits_n_bobs the Two cameras is active, can be disable off any minute, max in 4h 17m."
            }
        ],
        "tc_clothing": [
            {
                "title": "One camera",
                "disabled": false,
                "CHANGE?": "No!!",
                "this_run_time": "04:24:17",
                "run_type": "wait for it...",
                "old_run": "00:17:36",
                "min_cycle": "timedelta(hours=3)",
                "max_cycle": "timedelta(hours=10)",
                "status": "In tc_clothing the One camera is active, can be disable off any minute, max in 5h 35m."
            },
            {
                "title": "Checkpoint",
                "disabled": false,
                "CHANGE?": "No!!",
                "this_run_time": "48:12:16",
                "run_type": "wait for it...",
                "old_run": "11:28:12",
                "min_cycle": "timedelta(hours=72)",
                "max_cycle": "timedelta(hours=96)",
                "status": "In tc_clothing the Checkpoint is active, will disable in 23h 47m - 47h 47m."
            }
        ],
        "super_store": [
            {
                "title": "Two cameras",
                "disabled": false,
                "CHANGE?": "No!!",
                "this_run_time": "01:30:14",
                "run_type": "wait for it...",
                "old_run": "00:40:57",
                "min_cycle": "timedelta(hours=4, minutes=30)",
                "max_cycle": "timedelta(hours=14)",
                "status": "In super_store the Two cameras is active, will disable in 2h 59m - 12h 29m."
            },
            {
                "title": "Checkpoint",
                "disabled": false,
                "CHANGE?": "No!!",
                "this_run_time": "03:02:38",
                "run_type": "wait for it...",
                "old_run": "08:36:55",
                "min_cycle": "timedelta(hours=72)",
                "max_cycle": "timedelta(hours=96)",
                "status": "In super_store the Checkpoint is active, will disable in 68h 57m - 92h 57m."
            }
        ],
        "cyber_force": [
            {
                "title": "Two cameras",
                "disabled": false,
                "CHANGE?": "No!!",
                "this_run_time": "07:28:03",
                "run_type": "wait for it...",
                "old_run": "00:39:15",
                "min_cycle": "timedelta(hours=4, minutes=30)",
                "max_cycle": "timedelta(hours=14)",
                "status": "In cyber_force the Two cameras is active, can be disable off any minute, max in 6h 31m."
            },
            {
                "title": "One guard",
                "disabled": false,
                "CHANGE?": "YES!!",
                "this_run_time": "00:00:00",
                "run_type": "wait for it...",
                "old_run": "00:08:11",
                "min_cycle": "timedelta(hours=3, minutes=30)",
                "max_cycle": "timedelta(hours=5)",
                "status": "In cyber_force the One guard is active, will disable in 3h 30m - 5h 0m."
            }
        ],
        "pharmacy": [
            {
                "title": "Three cameras",
                "disabled": false,
                "CHANGE?": "No!!",
                "this_run_time": "03:20:08",
                "run_type": "wait for it...",
                "old_run": "00:26:14",
                "min_cycle": "timedelta(hours=4, minutes=30)",
                "max_cycle": "timedelta(hours=17)",
                "status": "In pharmacy the Three cameras is active, will disable in 1h 9m - 13h 39m."
            },
            {
                "title": "Checkpoint",
                "disabled": false,
                "CHANGE?": "No!!",
                "this_run_time": "94:49:47",
                "old_run": "07:59:26",
                "run_type": "wait for it...",
                "min_cycle": "timedelta(hours=72)",
                "max_cycle": "timedelta(hours=96)",
                "status": "In pharmacy the Checkpoint is active, can be disable off any minute, max in 1h 10m."
            }
        ],
        "big_als": [
            {
                "title": "Four cameras",
                "disabled": false,
                "CHANGE?": "No!!",
                "this_run_time": "00:16:42",
                "run_type": "wait for it...",
                "old_run": "00:17:40",
                "min_cycle": "timedelta(hours=4, minutes=30)",
                "max_cycle": "timedelta(hours=21)",
                "status": "In big_als the Four cameras is active, will disable in 4h 13m - 20h 43m."
            },
            {
                "title": "Two guards",
                "disabled": false,
                "CHANGE?": "No!!",
                "this_run_time": "00:24:53",
                "run_type": "wait for it...",
                "old_run": "00:00:00",
                "min_cycle": "timedelta(hours=7)",
                "max_cycle": "timedelta(hours=9)",
                "status": "In big_als the Two guards is active, will disable in 6h 35m - 8h 35m."
            }
        ],
        "jewelry_store": [
            {
                "title": "Three cameras",
                "disabled": false,
                "CHANGE?": "YES!!",
                "this_run_time": "00:00:00",
                "run_type": "wait for it...",
                "old_run": "00:25:51",
                "min_cycle": "timedelta(hours=4, minutes=30)",
                "max_cycle": "timedelta(hours=17)",
                "status": "In jewelry_store the Three cameras is active, will disable in 4h 30m - 17h 0m."
            },
            {
                "title": "One guard",
                "disabled": false,
                "CHANGE?": "No!!",
                "this_run_time": "04:24:17",
                "run_type": "wait for it...",
                "old_run": "00:00:00",
                "min_cycle": "timedelta(hours=3, minutes=30)",
                "max_cycle": "timedelta(hours=5)",
                "status": "In jewelry_store the One guard is active, can be disable off any minute, max in 35m 43s."
            }
        ]
    },
    "old_time": "2025-04-11T19:13:01.615690+00:00"
}