{
    "shoplifting": {
        "sallys_sweet_shop": [
            {
                "title": "One camera",
                "disabled": false,
                "CHANGE?": "No!!",
                "this_run_time": "01:29:05",
                "run_type": "wait for it...",
                "old_run": "00:24:12",
                "min_cycle": "timedelta(hours=3)",
                "max_cycle": "timedelta(hours=10)",
                "status": "In sallys_sweet_shop the One camera is active, will disable in 1h 30m - 8h 30m.",
                "icon": "red"
            }
        ],
        "Bits_n_bobs": [
            {
                "title": "Two cameras",
                "disabled": false,
                "CHANGE?": "No!!",
                "this_run_time": "10:17:28",
                "run_type": "wait for it...",
                "old_run": "00:40:12",
                "min_cycle": "timedelta(hours=4, minutes=30)",
                "max_cycle": "timedelta(hours=14)",
                "status": "In Bits_n_bobs the Two cameras is active, can be disabled any minute, max in 3h 42m.",
                "icon": "yellow"
            }
        ],
        "tc_clothing": [
            {
                "title": "One camera",
                "disabled": false,
                "CHANGE?": "No!!",
                "this_run_time": "00:00:00",
                "run_type": "wait for it...",
                "old_run": "00:08:07",
                "min_cycle": "timedelta(hours=3)",
                "max_cycle": "timedelta(hours=10)",
                "status": "In tc_clothing the One camera is active, will disable in 3h 0m - 10h 0m.",
                "icon": "red"
            },
            {
                "title": "Checkpoint",
                "disabled": false,
                "CHANGE?": "No!!",
                "this_run_time": "11:07:04",
                "run_type": "wait for it...",
                "old_run": "11:46:53",
                "min_cycle": "timedelta(hours=72)",
                "max_cycle": "timedelta(hours=96)",
                "status": "In tc_clothing the Checkpoint is active, will disable in 60h 52m - 84h 52m.",
                "icon": "red"
            }
        ],
        "super_store": [
            {
                "title": "Two cameras",
                "disabled": false,
                "CHANGE?": "No!!",
                "this_run_time": "01:45:55",
                "run_type": "wait for it...",
                "old_run": "00:17:41",
                "min_cycle": "timedelta(hours=4, minutes=30)",
                "max_cycle": "timedelta(hours=14)",
                "status": "In super_store the Two cameras is active, will disable in 2h 44m - 12h 14m.",
                "icon": "red"
            },
            {
                "title": "Checkpoint",
                "disabled": false,
                "CHANGE?": "YES!!",
                "this_run_time": "17:06:28",
                "run_type": "GO GO GO",
                "old_run": "05:51:44",
                "min_cycle": "timedelta(hours=72)",
                "max_cycle": "timedelta(hours=96)",
                "status": "In super_store the Checkpoint is active, will disable in 54h 53m - 78h 53m.",
                "icon": "red"
            }
        ],
        "cyber_force": [
            {
                "title": "Two cameras",
                "disabled": false,
                "CHANGE?": "No!!",
                "this_run_time": "01:17:51",
                "run_type": "wait for it...",
                "old_run": "00:41:02",
                "min_cycle": "timedelta(hours=4, minutes=30)",
                "max_cycle": "timedelta(hours=14)",
                "status": "In cyber_force the Two cameras is active, will disable in 3h 12m - 12h 42m.",
                "icon": "red"
            },
            {
                "title": "One guard",
                "disabled": false,
                "CHANGE?": "No!!",
                "this_run_time": "02:39:01",
                "run_type": "wait for it...",
                "old_run": "00:00:00",
                "min_cycle": "timedelta(hours=3, minutes=30)",
                "max_cycle": "timedelta(hours=5)",
                "status": "In cyber_force the One guard is active, will disable in 50m 59s - 2h 20m.",
                "icon": "red"
            }
        ],
        "pharmacy": [
            {
                "title": "Three cameras",
                "disabled": false,
                "CHANGE?": "No!!",
                "this_run_time": "03:06:38",
                "run_type": "wait for it...",
                "old_run": "00:43:35",
                "min_cycle": "timedelta(hours=4, minutes=30)",
                "max_cycle": "timedelta(hours=17)",
                "status": "In pharmacy the Three cameras is active, will disable in 1h 23m - 13h 53m.",
                "icon": "red"
            },
            {
                "title": "Checkpoint",
                "disabled": false,
                "CHANGE?": "No!!",
                "this_run_time": "16:12:28",
                "old_run": "09:49:22",
                "run_type": "wait for it...",
                "min_cycle": "timedelta(hours=72)",
                "max_cycle": "timedelta(hours=96)",
                "status": "In pharmacy the Checkpoint is active, will disable in 55h 47m - 79h 47m.",
                "icon": "red"
            }
        ],
        "big_als": [
            {
                "title": "Four cameras",
                "disabled": false,
                "CHANGE?": "No!!",
                "this_run_time": "14:03:52",
                "run_type": "wait for it...",
                "old_run": "00:16:16",
                "min_cycle": "timedelta(hours=4, minutes=30)",
                "max_cycle": "timedelta(hours=21)",
                "status": "In big_als the Four cameras is active, can be disabled any minute, max in 6h 56m.",
                "icon": "yellow"
            },
            {
                "title": "Two guards",
                "disabled": false,
                "CHANGE?": "No!!",
                "this_run_time": "05:43:15",
                "run_type": "wait for it...",
                "old_run": "00:07:58",
                "min_cycle": "timedelta(hours=7)",
                "max_cycle": "timedelta(hours=9)",
                "status": "In big_als the Two guards is active, will disable in 1h 16m - 3h 16m.",
                "icon": "red"
            }
        ],
        "jewelry_store": [
            {
                "title": "Three cameras",
                "disabled": false,
                "CHANGE?": "YES!!",
                "this_run_time": "05:12:14",
                "run_type": "GO GO GO",
                "old_run": "00:22:56",
                "min_cycle": "timedelta(hours=4, minutes=30)",
                "max_cycle": "timedelta(hours=17)",
                "status": "In jewelry_store the Three cameras is active, can be disabled any minute, max in 11h 47m.",
                "icon": "yellow"
            },
            {
                "title": "One guard",
                "disabled": false,
                "CHANGE?": "No!!",
                "this_run_time": "02:19:39",
                "run_type": "wait for it...",
                "old_run": "00:00:00",
                "min_cycle": "timedelta(hours=3, minutes=30)",
                "max_cycle": "timedelta(hours=5)",
                "status": "In jewelry_store the One guard is active, will disable in 1h 10m - 2h 40m.",
                "icon": "red"
            }
        ]
    },
    "old_time": "2025-04-23T00:55:51.412451+00:00",
    "icon": "yellow"
}