{
    "shoplifting": {
        "sallys_sweet_shop": [
            {
                "title": "One camera",
                "disabled": true,
                "CHANGE?": "No!!",
                "this_run_time": "00:25:21",
                "run_type": "wait for it...",
                "old_run": "04:51:53",
                "min_cycle": "timedelta(hours=3)",
                "max_cycle": "timedelta(hours=10)",
                "status": "In sallys_sweet_shop the One camera is disabled.",
                "icon": "green"
            }
        ],
        "Bits_n_bobs": [
            {
                "title": "Two cameras",
                "disabled": false,
                "CHANGE?": "No!!",
                "this_run_time": "03:32:27",
                "run_type": "wait for it...",
                "old_run": "00:00:00",
                "min_cycle": "timedelta(hours=4, minutes=30)",
                "max_cycle": "timedelta(hours=14)",
                "status": "In Bits_n_bobs the Two cameras is active, will disable in 57m 33s - 10h 27m.",
                "icon": "red"
            }
        ],
        "tc_clothing": [
            {
                "title": "One camera",
                "disabled": false,
                "CHANGE?": "No!!",
                "this_run_time": "05:33:51",
                "run_type": "wait for it...",
                "old_run": "00:00:00",
                "min_cycle": "timedelta(hours=3)",
                "max_cycle": "timedelta(hours=10)",
                "status": "In tc_clothing the One camera is active, can be disabled any minute, max in 4h 26m.",
                "icon": "yellow"
            },
            {
                "title": "Checkpoint",
                "disabled": false,
                "CHANGE?": "No!!",
                "this_run_time": "14:22:08",
                "run_type": "wait for it...",
                "old_run": "11:41:57",
                "min_cycle": "timedelta(hours=72)",
                "max_cycle": "timedelta(hours=96)",
                "status": "In tc_clothing the Checkpoint is active, will disable in 57h 37m - 81h 37m.",
                "icon": "red"
            }
        ],
        "super_store": [
            {
                "title": "Two cameras",
                "disabled": false,
                "CHANGE?": "No!!",
                "this_run_time": "07:22:34",
                "run_type": "wait for it...",
                "old_run": "00:43:16",
                "min_cycle": "timedelta(hours=4, minutes=30)",
                "max_cycle": "timedelta(hours=14)",
                "status": "In super_store the Two cameras is active, can be disabled any minute, max in 6h 37m.",
                "icon": "yellow"
            },
            {
                "title": "Checkpoint",
                "disabled": false,
                "CHANGE?": "YES!!",
                "this_run_time": "35:31:35",
                "run_type": "GO GO GO",
                "old_run": "07:15:16",
                "min_cycle": "timedelta(hours=72)",
                "max_cycle": "timedelta(hours=96)",
                "status": "In super_store the Checkpoint is active, will disable in 36h 28m - 60h 28m.",
                "icon": "red"
            }
        ],
        "cyber_force": [
            {
                "title": "Two cameras",
                "disabled": false,
                "CHANGE?": "No!!",
                "this_run_time": "11:14:05",
                "run_type": "wait for it...",
                "old_run": "00:36:16",
                "min_cycle": "timedelta(hours=4, minutes=30)",
                "max_cycle": "timedelta(hours=14)",
                "status": "In cyber_force the Two cameras is active, can be disabled any minute, max in 2h 45m.",
                "icon": "yellow"
            },
            {
                "title": "One guard",
                "disabled": false,
                "CHANGE?": "No!!",
                "this_run_time": "13:23:13",
                "run_type": "wait for it...",
                "old_run": "00:00:00",
                "min_cycle": "timedelta(hours=3, minutes=30)",
                "max_cycle": "timedelta(hours=5)",
                "status": "In cyber_force the One guard is active, but due to error, can't give estimated time.",
                "icon": "red"
            }
        ],
        "pharmacy": [
            {
                "title": "Three cameras",
                "disabled": false,
                "CHANGE?": "No!!",
                "this_run_time": "07:40:07",
                "run_type": "wait for it...",
                "old_run": "00:29:26",
                "min_cycle": "timedelta(hours=4, minutes=30)",
                "max_cycle": "timedelta(hours=17)",
                "status": "In pharmacy the Three cameras is active, can be disabled any minute, max in 9h 19m.",
                "icon": "yellow"
            },
            {
                "title": "Checkpoint",
                "disabled": false,
                "CHANGE?": "No!!",
                "this_run_time": "32:01:53",
                "old_run": "08:09:28",
                "run_type": "wait for it...",
                "min_cycle": "timedelta(hours=72)",
                "max_cycle": "timedelta(hours=96)",
                "status": "In pharmacy the Checkpoint is active, will disable in 39h 58m - 63h 58m.",
                "icon": "red"
            }
        ],
        "big_als": [
            {
                "title": "Four cameras",
                "disabled": false,
                "CHANGE?": "No!!",
                "this_run_time": "05:33:51",
                "run_type": "wait for it...",
                "old_run": "00:25:37",
                "min_cycle": "timedelta(hours=4, minutes=30)",
                "max_cycle": "timedelta(hours=21)",
                "status": "In big_als the Four cameras is active, can be disabled any minute, max in 15h 26m.",
                "icon": "yellow"
            },
            {
                "title": "Two guards",
                "disabled": false,
                "CHANGE?": "No!!",
                "this_run_time": "14:14:26",
                "run_type": "wait for it...",
                "old_run": "00:00:00",
                "min_cycle": "timedelta(hours=7)",
                "max_cycle": "timedelta(hours=9)",
                "status": "In big_als the Two guards is active, but due to error, can't give estimated time.",
                "icon": "red"
            }
        ],
        "jewelry_store": [
            {
                "title": "Three cameras",
                "disabled": false,
                "CHANGE?": "YES!!",
                "this_run_time": "05:33:51",
                "run_type": "GO GO GO",
                "old_run": "00:37:57",
                "min_cycle": "timedelta(hours=4, minutes=30)",
                "max_cycle": "timedelta(hours=17)",
                "status": "In jewelry_store the Three cameras is active, can be disabled any minute, max in 11h 26m.",
                "icon": "yellow"
            },
            {
                "title": "One guard",
                "disabled": false,
                "CHANGE?": "No!!",
                "this_run_time": "08:40:51",
                "run_type": "wait for it...",
                "old_run": "00:00:00",
                "min_cycle": "timedelta(hours=3, minutes=30)",
                "max_cycle": "timedelta(hours=5)",
                "status": "In jewelry_store the One guard is active, but due to error, can't give estimated time.",
                "icon": "red"
            }
        ]
    },
    "old_time": "2025-04-20T07:12:05.909535+00:00",
    "icon": "green"
}